{
  "universities": [
    {
      "id": 1,
      "name": "Boğaziçi Universiteti",
      "country": "Türkiyə",
      "city": "İstanbul",
      "ielts_min": 6.5,
      "toefl_min": 87,
      "gpa_min": 3.0,
      "fields": [
        "Kompüter Elmləri",
        "Biznes",
        "Mühəndislik",
        "Sosial Elmlər"
      ],
      "tuition_usd_per_year": 800,
      "language": "İngilis/Türk",
      "deadline": "Mart",
      "scholarship_available": true,
      "website": "https://www.boun.edu.tr"
    },
    {
      "id": 2,
      "name": "ODTÜ (Orta Doğu Texniki Universiteti)",
      "country": "Türkiyə",
      "city": "Ankara",
      "ielts_min": 6.5,
      "toefl_min": 87,
      "gpa_min": 3.0,
      "fields": [
        "Mühəndislik",
        "Kompüter Elmləri",
        "Memarlıq",
        "Təbiət Elmləri"
      ],
      "tuition_usd_per_year": 700,
      "language": "İngilis",
      "deadline": "Mart",
      "scholarship_available": true,
      "website": "https://www.metu.edu.tr"
    },
    {
      "id": 3,
      "name": "Koç Universiteti",
      "country": "Türkiyə",
      "city": "İstanbul",
      "ielts_min": 7.0,
      "toefl_min": 100,
      "gpa_min": 3.2,
      "fields": [
        "Biznes (MBA)",
        "Hüquq",
        "Tibb",
        "Mühəndislik"
      ],
      "tuition_usd_per_year": 12000,
      "language": "İngilis",
      "deadline": "Fevral",
      "scholarship_available": true,
      "website": "https://www.ku.edu.tr"
    },
    {
      "id": 4,
      "name": "Sabancı Universiteti",
      "country": "Türkiyə",
      "city": "İstanbul",
      "ielts_min": 6.5,
      "toefl_min": 87,
      "gpa_min": 3.0,
      "fields": [
        "Mühəndislik",
        "Biznes",
        "Sosial Elmlər",
        "Süni İntellekt"
      ],
      "tuition_usd_per_year": 10000,
      "language": "İngilis",
      "deadline": "Mart",
      "scholarship_available": true,
      "website": "https://www.sabanciuniv.edu"
    },
    {
      "id": 5,
      "name": "Bilkent Universiteti",
      "country": "Türkiyə",
      "city": "Ankara",
      "ielts_min": 6.5,
      "toefl_min": 87,
      "gpa_min": 3.0,
      "fields": [
        "Kompüter Elmləri",
        "Biznes",
        "Mühəndislik",
        "İncəsənət"
      ],
      "tuition_usd_per_year": 9000,
      "language": "İngilis",
      "deadline": "Mart",
      "scholarship_available": true,
      "website": "https://www.bilkent.edu.tr"
    },
    {
      "id": 6,
      "name": "TU Munich (Texniki Universitet München)",
      "country": "Almaniya",
      "city": "Münhen",
      "ielts_min": 6.5,
      "toefl_min": 88,
      "gpa_min": 3.0,
      "fields": [
        "Mühəndislik",
        "İnformatika",
        "Təbiət Elmləri",
        "Menecment"
      ],
      "tuition_usd_per_year": 300,
      "language": "İngilis/Alman",
      "deadline": "Yanvar",
      "scholarship_available": true,
      "website": "https://www.tum.de"
    },
    {
      "id": 7,
      "name": "Heidelberg Universiteti",
      "country": "Almaniya",
      "city": "Heidelberg",
      "ielts_min": 6.5,
      "toefl_min": 88,
      "gpa_min": 3.0,
      "fields": [
        "Tibb",
        "Biologiya",
        "Hüquq",
        "Sosial Elmlər"
      ],
      "tuition_usd_per_year": 300,
      "language": "Alman/İngilis",
      "deadline": "Yanvar",
      "scholarship_available": true,
      "website": "https://www.uni-heidelberg.de"
    },
    {
      "id": 8,
      "name": "LMU München",
      "country": "Almaniya",
      "city": "Münhen",
      "ielts_min": 6.5,
      "toefl_min": 88,
      "gpa_min": 2.8,
      "fields": [
        "Tibb",
        "Hüquq",
        "İqtisadiyyat",
        "Humanitar Elmlər"
      ],
      "tuition_usd_per_year": 300,
      "language": "Alman/İngilis",
      "deadline": "Yanvar",
      "scholarship_available": false,
      "website": "https://www.lmu.de"
    },
    {
      "id": 9,
      "name": "Humboldt Universiteti Berlin",
      "country": "Almaniya",
      "city": "Berlin",
      "ielts_min": 6.0,
      "toefl_min": 80,
      "gpa_min": 2.8,
      "fields": [
        "Humanitar Elmlər",
        "Hüquq",
        "Təbiət Elmləri",
        "Sosial Elmlər"
      ],
      "tuition_usd_per_year": 300,
      "language": "Alman/İngilis",
      "deadline": "Mart",
      "scholarship_available": true,
      "website": "https://www.hu-berlin.de"
    },
    {
      "id": 10,
      "name": "FU Berlin (Azad Universitet Berlin)",
      "country": "Almaniya",
      "city": "Berlin",
      "ielts_min": 6.0,
      "toefl_min": 80,
      "gpa_min": 2.8,
      "fields": [
        "Siyasi Elmlər",
        "Tarix",
        "Hüquq",
        "İqtisadiyyat"
      ],
      "tuition_usd_per_year": 300,
      "language": "Alman/İngilis",
      "deadline": "Mart",
      "scholarship_available": false,
      "website": "https://www.fu-berlin.de"
    },
    {
      "id": 11,
      "name": "Delft Texniki Universiteti",
      "country": "Hollandiya",
      "city": "Delft",
      "ielts_min": 6.5,
      "toefl_min": 90,
      "gpa_min": 3.0,
      "fields": [
        "Mühəndislik",
        "Memarlıq",
        "Aeronavtika",
        "İnformatika"
      ],
      "tuition_usd_per_year": 18000,
      "language": "İngilis",
      "deadline": "Yanvar",
      "scholarship_available": true,
      "website": "https://www.tudelft.nl"
    },
    {
      "id": 12,
      "name": "Amsterdam Universiteti",
      "country": "Hollandiya",
      "city": "Amsterdam",
      "ielts_min": 6.5,
      "toefl_min": 92,
      "gpa_min": 3.0,
      "fields": [
        "Biznes",
        "Hüquq",
        "Sosial Elmlər",
        "İnformatika"
      ],
      "tuition_usd_per_year": 16000,
      "language": "İngilis",
      "deadline": "Yanvar",
      "scholarship_available": true,
      "website": "https://www.uva.nl"
    },
    {
      "id": 13,
      "name": "Eindhoven Texniki Universiteti",
      "country": "Hollandiya",
      "city": "Eindhoven",
      "ielts_min": 6.5,
      "toefl_min": 90,
      "gpa_min": 3.0,
      "fields": [
        "Mühəndislik",
        "Elektrotexnika",
        "İnformatika",
        "Dizayn"
      ],
      "tuition_usd_per_year": 17000,
      "language": "İngilis",
      "deadline": "Yanvar",
      "scholarship_available": true,
      "website": "https://www.tue.nl"
    },
    {
      "id": 14,
      "name": "KU Leuven",
      "country": "Belçika",
      "city": "Leuven",
      "ielts_min": 6.5,
      "toefl_min": 88,
      "gpa_min": 3.0,
      "fields": [
        "Tibb",
        "Mühəndislik",
        "Hüquq",
        "İqtisadiyyat"
      ],
      "tuition_usd_per_year": 5000,
      "language": "İngilis/Holland",
      "deadline": "Mart",
      "scholarship_available": true,
      "website": "https://www.kuleuven.be"
    },
    {
      "id": 15,
      "name": "Uppsala Universiteti",
      "country": "İsveç",
      "city": "Uppsala",
      "ielts_min": 6.5,
      "toefl_min": 90,
      "gpa_min": 3.0,
      "fields": [
        "Tibb",
        "Hüquq",
        "Sosial Elmlər",
        "Təbiət Elmləri"
      ],
      "tuition_usd_per_year": 13000,
      "language": "İngilis",
      "deadline": "Yanvar",
      "scholarship_available": true,
      "website": "https://www.uu.se"
    },
    {
      "id": 16,
      "name": "KTH Royal Institute of Technology",
      "country": "İsveç",
      "city": "Stokholm",
      "ielts_min": 6.5,
      "toefl_min": 90,
      "gpa_min": 3.0,
      "fields": [
        "Mühəndislik",
        "İnformatika",
        "Texnologiya",
        "Arxitektura"
      ],
      "tuition_usd_per_year": 14000,
      "language": "İngilis",
      "deadline": "Yanvar",
      "scholarship_available": true,
      "website": "https://www.kth.se"
    },
    {
      "id": 17,
      "name": "ETH Zürich",
      "country": "İsveçrə",
      "city": "Zürix",
      "ielts_min": 7.0,
      "toefl_min": 100,
      "gpa_min": 3.5,
      "fields": [
        "Mühəndislik",
        "Kompüter Elmləri",
        "Fizika",
        "Riyaziyyat"
      ],
      "tuition_usd_per_year": 1500,
      "language": "İngilis/Alman",
      "deadline": "Dekabr",
      "scholarship_available": true,
      "website": "https://www.ethz.ch"
    },
    {
      "id": 18,
      "name": "Varşava Universiteti",
      "country": "Polşa",
      "city": "Varşava",
      "ielts_min": 6.0,
      "toefl_min": 80,
      "gpa_min": 2.8,
      "fields": [
        "İqtisadiyyat",
        "Hüquq",
        "İnformatika",
        "Sosial Elmlər"
      ],
      "tuition_usd_per_year": 3000,
      "language": "İngilis/Polyak",
      "deadline": "May",
      "scholarship_available": false,
      "website": "https://www.uw.edu.pl"
    },
    {
      "id": 19,
      "name": "Çex Texniki Universiteti (CTU Prague)",
      "country": "Çexiya",
      "city": "Praqa",
      "ielts_min": 6.0,
      "toefl_min": 80,
      "gpa_min": 2.8,
      "fields": [
        "Mühəndislik",
        "Arxitektura",
        "İnformatika",
        "Nəqliyyat"
      ],
      "tuition_usd_per_year": 2000,
      "language": "İngilis",
      "deadline": "Aprel",
      "scholarship_available": false,
      "website": "https://www.cvut.cz"
    },
    {
      "id": 20,
      "name": "Tbilisi Dövlət Universiteti",
      "country": "Gürcüstan",
      "city": "Tbilisi",
      "ielts_min": 5.5,
      "toefl_min": 72,
      "gpa_min": 2.5,
      "fields": [
        "Hüquq",
        "İqtisadiyyat",
        "Beynəlxalq Münasibətlər",
        "Humanitar Elmlər"
      ],
      "tuition_usd_per_year": 2500,
      "language": "İngilis/Gürcü",
      "deadline": "İyun",
      "scholarship_available": false,
      "website": "https://www.tsu.ge"
    },
    {
      "id": 21,
      "name": "Boloniya Universiteti",
      "country": "İtaliya",
      "city": "Boloniya",
      "ielts_min": 6.0,
      "toefl_min": 80,
      "gpa_min": 2.7,
      "fields": [
        "Kompüter Elmləri",
        "İqtisadiyyat",
        "Beynəlxalq Münasibətlər",
        "Humanitar Elmlər"
      ],
      "tuition_usd_per_year": 1200,
      "language": "İngilis/İtalyan",
      "deadline": "Aprel",
      "scholarship_available": true,
      "website": "https://www.unibo.it"
    },
    {
      "id": 22,
      "name": "Milano Politexnik Universiteti",
      "country": "İtaliya",
      "city": "Milan",
      "ielts_min": 6.0,
      "toefl_min": 78,
      "gpa_min": 2.8,
      "fields": [
        "Mühəndislik",
        "Arxitektura",
        "Dizayn",
        "Süni İntellekt"
      ],
      "tuition_usd_per_year": 1500,
      "language": "İngilis",
      "deadline": "Fevral",
      "scholarship_available": true,
      "website": "https://www.polimi.it"
    },
    {
      "id": 23,
      "name": "Sapienza Roma Universiteti",
      "country": "İtaliya",
      "city": "Roma",
      "ielts_min": 6.0,
      "toefl_min": 80,
      "gpa_min": 2.6,
      "fields": [
        "Klassik Elmlər",
        "Fizika",
        "Kompüter Elmləri",
        "Tibb"
      ],
      "tuition_usd_per_year": 1000,
      "language": "İngilis/İtalyan",
      "deadline": "May",
      "scholarship_available": true,
      "website": "https://www.uniroma1.it"
    },
    {
      "id": 24,
      "name": "Vyan Dövlət Universiteti",
      "country": "Avstriya",
      "city": "Vyana",
      "ielts_min": 6.5,
      "toefl_min": 87,
      "gpa_min": 2.8,
      "fields": [
        "İqtisadiyyat",
        "İnformatika",
        "Psixologiya",
        "Xarici Dillər"
      ],
      "tuition_usd_per_year": 1600,
      "language": "Alman/İngilis",
      "deadline": "Aprel",
      "scholarship_available": false,
      "website": "https://www.univie.ac.at"
    },
    {
      "id": 25,
      "name": "Tokyo Universiteti",
      "country": "Yaponiya",
      "city": "Tokyo",
      "ielts_min": 7.0,
      "toefl_min": 100,
      "gpa_min": 3.4,
      "fields": [
        "Fizika",
        "Mühəndislik",
        "İnformatika",
        "İqtisadiyyat"
      ],
      "tuition_usd_per_year": 5000,
      "language": "Yapon/İngilis",
      "deadline": "Dekabr",
      "scholarship_available": true,
      "website": "https://www.u-tokyo.ac.jp"
    },
    {
      "id": 26,
      "name": "Seoul Milli Universiteti",
      "country": "Cənubi Koreya",
      "city": "Seoul",
      "ielts_min": 6.5,
      "toefl_min": 85,
      "gpa_min": 3.2,
      "fields": [
        "Kompüter Elmləri",
        "Mühəndislik",
        "Biznes",
        "Kimya"
      ],
      "tuition_usd_per_year": 6000,
      "language": "Koreya/İngilis",
      "deadline": "Mart",
      "scholarship_available": true,
      "website": "https://www.snu.ac.kr"
    },
    {
      "id": 27,
      "name": "Budapeşt Texnologiya və İqtisadiyyat Universiteti",
      "country": "Macarıstan",
      "city": "Budapeşt",
      "ielts_min": 6.0,
      "toefl_min": 80,
      "gpa_min": 2.7,
      "fields": [
        "Mühəndislik",
        "İnformatika",
        "Riyaziyyat",
        "İqtisadiyyat"
      ],
      "tuition_usd_per_year": 3500,
      "language": "İngilis",
      "deadline": "Aprel",
      "scholarship_available": true,
      "website": "https://www.bme.hu"
    },
    {
      "id": 28,
      "name": "Tallin Texnoloji Universiteti (TalTech)",
      "country": "Estoniya",
      "city": "Tallin",
      "ielts_min": 6.0,
      "toefl_min": 72,
      "gpa_min": 2.8,
      "fields": [
        "Kiber-təhlükəsizlik",
        "İnformatika",
        "Biznes",
        "Robototexnika"
      ],
      "tuition_usd_per_year": 4000,
      "language": "İngilis",
      "deadline": "May",
      "scholarship_available": true,
      "website": "https://taltech.ee"
    }
  ]
}